vracer/__init__.py
vracer/snoop_debug_some.py
vracer/snoop/__init__.py
vracer/snoop/configuration.py
vracer/snoop/formatting.py
vracer/snoop/pp_module.py
vracer/snoop/tracer.py
vracer/snoop/utils.py
vracer/snoop/variables.py
vracer-0.1.0.dist-info/LICENSE
vracer-0.1.0.dist-info/METADATA
vracer-0.1.0.dist-info/WHEEL
vracer-0.1.0.dist-info/top_level.txt
vracer-0.1.0.dist-info/RECORD
